LICENSE
MANIFEST.in
README.rst
requirements.txt
setup.py
python_object_extractor/__init__.py
python_object_extractor/attributes.py
python_object_extractor/collections.py
python_object_extractor/descriptors.py
python_object_extractor/exceptions.py
python_object_extractor/graph.py
python_object_extractor/imports.py
python_object_extractor/inspection.py
python_object_extractor/main.py
python_object_extractor/modules.py
python_object_extractor/output.py
python_object_extractor/references.py
python_object_extractor/sources.py
python_object_extractor/substitutions.py
python_object_extractor/symbols.py
python_object_extractor.egg-info/PKG-INFO
python_object_extractor.egg-info/SOURCES.txt
python_object_extractor.egg-info/dependency_links.txt
python_object_extractor.egg-info/entry_points.txt
python_object_extractor.egg-info/namespace_packages.txt
python_object_extractor.egg-info/requires.txt
python_object_extractor.egg-info/top_level.txt